{"anncomplete": true, "metas": {}, "annotatable": {"parts": ["s1h1", "s2h1", "s2p1"]}, "sources": [{"id": "12429849", "name": "ORIG", "url": "http://www.ncbi.nlm.nih.gov/pubmed/12429849"}, {"id": "12429849", "name": "PMID", "url": "http://www.ncbi.nlm.nih.gov/pubmed/12429849"}], "relations": [], "entities": [{"confidence": {"prob": 1, "who": ["user:shrikant"], "state": ""}, "part": "s1h1", "normalizations": {}, "classId": "e_3", "offsets": [{"start": 33, "text": "human"}], "fields": {}}, {"confidence": {"prob": 1, "who": ["user:shrikant"], "state": ""}, "part": "s1h1", "normalizations": {}, "classId": "e_2", "offsets": [{"start": 39, "text": "nucleolus"}], "fields": {}}, {"confidence": {"prob": 1, "who": ["user:shrikant"], "state": ""}, "part": "s2p1", "normalizations": {}, "classId": "e_2", "offsets": [{"start": 34, "text": "nucleolus"}], "fields": {}}, {"confidence": {"prob": 1, "who": ["user:shrikant"], "state": ""}, "part": "s2p1", "normalizations": {}, "classId": "e_2", "offsets": [{"start": 157, "text": "nuclear"}], "fields": {}}, {"confidence": {"prob": 1, "who": ["user:shrikant"], "state": ""}, "part": "s2p1", "normalizations": {}, "classId": "e_2", "offsets": [{"start": 340, "text": "nucleoli"}], "fields": {}}, {"confidence": {"prob": 1, "who": ["user:shrikant"], "state": ""}, "part": "s2p1", "normalizations": {}, "classId": "e_2", "offsets": [{"start": 422, "text": "nucleolar"}], "fields": {}}, {"confidence": {"prob": 1, "who": ["user:shrikant"], "state": ""}, "part": "s2p1", "normalizations": {}, "classId": "e_2", "offsets": [{"start": 567, "text": "nucleolar"}], "fields": {}}, {"confidence": {"prob": 1, "who": ["user:shrikant"], "state": ""}, "part": "s2p1", "normalizations": {}, "classId": "e_2", "offsets": [{"start": 698, "text": "nucleoli"}], "fields": {}}, {"confidence": {"prob": 1, "who": ["user:shrikant"], "state": ""}, "part": "s2p1", "normalizations": {}, "classId": "e_2", "offsets": [{"start": 1005, "text": "nucleoli"}], "fields": {}}, {"confidence": {"prob": 1, "who": ["user:shrikant"], "state": ""}, "part": "s2p1", "normalizations": {}, "classId": "e_2", "offsets": [{"start": 1052, "text": "nucleoli"}], "fields": {}}]}